herding/__init__.py
herding/animation/__init__.py
herding/animation/discrepancyanimation2d.py
herding/animation/landmarkanimation2d.py
herding/gaussianherding/__init__.py
herding/gaussiankernel/__init__.py
herding/gaussiankernel/analyticallandmarkexpectation.py
herding/gaussiankernel/analyticallandmarkexpectationmulti.py
herding/gaussiankernel/gaussiankernel.py
herding/gaussiankernel/gaussiankernelmulti.py
herding/gaussiankernel/numericallandmarkexpectation.py
herding/gaussiankernel/numericallandmarkexpectationmulti.py
herding-0.0.2.dist-info/LICENSE
herding-0.0.2.dist-info/METADATA
herding-0.0.2.dist-info/WHEEL
herding-0.0.2.dist-info/entry_points.txt
herding-0.0.2.dist-info/top_level.txt
herding-0.0.2.dist-info/RECORD
