Metadata-Version: 2.2
Name: herding
Version: 0.0.2
Summary: Kernel herding
Home-page: https://github.com/microprediction/herding
Author: microprediction
Author-email: peter.cotton@microprediction.com
License: MIT
Classifier: License :: OSI Approved :: MIT License
Classifier: Programming Language :: Python :: 3
Classifier: Programming Language :: Python :: 3.12
License-File: LICENSE
Requires-Dist: numpy
Requires-Dist: randomcov
Dynamic: author
Dynamic: author-email
Dynamic: classifier
Dynamic: description
Dynamic: description-content-type
Dynamic: home-page
Dynamic: license
Dynamic: requires-dist
Dynamic: summary
